{
  "$schema": "https://open-toolset-protocol.org/schemas/toolsets.schema.json",
  "toolset_name": "phase-gated",
  "version": "0.1.0",
  "policies": {
    "default_action": "allow",
    "forbidden_args": []
  },
  "tools": [
    {
      "name": "libcst",
      "phase": "surgery",
      "category": "logic-substrate",
      "verification_mode": "deterministic",
      "description": "Python AST transform — surgery only",
      "priority": 80
    },
    {
      "name": "git-status",
      "phase": "reconnaissance",
      "category": "navigation",
      "verification_mode": "deterministic",
      "priority": 60
    }
  ]
}
